Metadata-Version: 1.0
Name: micropython-uffmpeg
Version: 0.0.0
Summary: (deprecated)
Home-page: https://github.com/pfalcon/pycopy-uffmpeg
Author: Paul Sokolovsky
Author-email: pfalcon@users.sourceforge.net
License: MIT
Platform: UNKNOWN
